MANIFEST.in
README.txt
requirements-devel.txt
requirements.txt
setup.py
Brownstone.egg-info/PKG-INFO
Brownstone.egg-info/SOURCES.txt
Brownstone.egg-info/dependency_links.txt
Brownstone.egg-info/top_level.txt
brownstone/__init__.py
brownstone/ctrl.py
brownstone/forms.py
brownstone/mail.py
brownstone/wsgi.py