Metadata-Version: 1.0
Name: Brownstone
Version: 1.0a1
Summary: A small WSGI application framework based on WebOb.
Home-page: http://bitbucket.org/shadytrees/brownstone/src/
Author: Hao Lian
Author-email: me / haolian / org
License: BSD
Platform: UNKNOWN
